{
    "last_updated": "2026-04-23 00:55",
    "prices": [
        {
            "source": "데포로쥬",
            "price": "3,025원",
            "status": "-5.4%"
        },
        {
            "source": "켄라우헬",
            "price": "2,207원",
            "status": "-6.2%"
        },
        {
            "source": "에바",
            "price": "2,243원",
            "status": "+0.1%"
        },
        {
            "source": "데컨",
            "price": "1,946원",
            "status": "-3.6%"
        },
        {
            "source": "듀크데필",
            "price": "2,112원",
            "status": "-6.8%"
        }
    ]
}