{
    "last_updated": "2026-06-05 22:27",
    "prices": [
        {
            "source": "데포로쥬",
            "price": "2,594원",
            "status": "+1.1%"
        },
        {
            "source": "데컨",
            "price": "1,280원",
            "status": "+1.3%"
        },
        {
            "source": "켄라우헬",
            "price": "1,500원",
            "status": "-2.6%"
        },
        {
            "source": "에바",
            "price": "1,017원",
            "status": "+1.7%"
        },
        {
            "source": "듀크데필",
            "price": "1,198원",
            "status": "-0.2%"
        }
    ]
}