{
    "last_updated": "2026-06-15 06:40",
    "prices": [
        {
            "source": "에바",
            "price": "800원",
            "status": "+7.8%"
        },
        {
            "source": "데포로쥬",
            "price": "1,400원",
            "status": "-12.5%"
        },
        {
            "source": "데컨",
            "price": "890원",
            "status": "+1.0%"
        },
        {
            "source": "듀크데필",
            "price": "840원",
            "status": "-5.6%"
        },
        {
            "source": "켄라우헬",
            "price": "1,030원",
            "status": "-4.5%"
        }
    ]
}